{"is_source_file": false, "format": "", "description": "", "external_files": [], "external_methods": [], "published": [], "classes": [], "methods": [], "calls": [], "search-terms": [], "state": 2, "file_id": 8, "knowledge_revision": 24, "git_revision": "a05f651289fee09240a314db3e1e037fdae772e5", "hash": "36b556e3b173447a9b2492132ed293d7", "format-version": 4, "code-base-name": "nextjs_frontend", "filename": "nextjs_frontend/package.json", "revision_history": [{"24": "a05f651289fee09240a314db3e1e037fdae772e5"}]}