{"is_source_file": true, "format": "TypeScript (TSX)", "description": "This file implements a React component for a checkout/payment page in a Next.js frontend. It handles initiating a payment intent via an API and displays relevant UI elements and status.", "external_files": ["@/lib/api"], "external_methods": ["apiFetch"], "published": ["default"], "classes": [], "methods": [{"name": "CheckoutClient", "description": "React component managing the payment initiation process, state, and UI."}, {"name": "startPayment", "description": "Asynchronous function to create a payment intent via API fetch and update state accordingly."}], "calls": ["apiFetch"], "search-terms": ["Next.js payment page", "Stripe integration placeholder", "useSearchParams", "checkout UI", "payment intent"], "state": 2, "file_id": 27, "knowledge_revision": 143, "git_revision": "7a9e496299372655cb7cb41c60035592b2e697fd", "revision_history": [{"57": ""}, {"95": "8b31c15ee3725154e7683c210c366224aa814240"}, {"118": "8b31c15ee3725154e7683c210c366224aa814240"}, {"137": "8b31c15ee3725154e7683c210c366224aa814240"}, {"143": "7a9e496299372655cb7cb41c60035592b2e697fd"}], "ctags": [], "hash": "4dc6504a8cc63d8cb4fca6578da054b5", "format-version": 4, "code-base-name": "nextjs_frontend", "filename": "nextjs_frontend/src/app/payments/checkout/page.tsx"}